{
    "objects": [
        {
            "attributes": {
                "description": "",
                "kibanaSavedObjectMeta": {
                    "searchSourceJSON": "{\"filter\": []}"
                },
                "savedSearchId": "MongoDB-search-ecs",
                "title": "Hosts [Metricbeat MongoDB] ECS",
                "uiStateJSON": "{\"vis\": {\"params\": {\"sort\": {\"columnIndex\": null, \"direction\": null}}}}",
                "version": 1,
                "visState": "{\"params\": {\"showMeticsAtAllLevels\": false, \"showTotal\": false, \"perPage\": 10, \"totalFunc\": \"sum\", \"showPartialRows\": false, \"sort\": {\"columnIndex\": null, \"direction\": null}}, \"type\": \"table\", \"title\": \"Hosts [Metricbeat MongoDB] ECS\", \"aggs\": [{\"type\": \"avg\", \"enabled\": true, \"id\": \"1\", \"schema\": \"metric\", \"params\": {\"customLabel\": \"Number of connections\", \"field\": \"mongodb.status.connections.current\"}}, {\"type\": \"terms\", \"enabled\": true, \"id\": \"2\", \"schema\": \"bucket\", \"params\": {\"orderBy\": \"1\", \"size\": 5, \"order\": \"desc\", \"field\": \"service.address\"}}, {\"type\": \"avg\", \"enabled\": true, \"id\": \"3\", \"schema\": \"metric\", \"params\": {\"customLabel\": \"Arch\", \"field\": \"mongodb.status.memory.bits\"}}, {\"type\": \"avg\", \"enabled\": true, \"id\": \"4\", \"schema\": \"metric\", \"params\": {\"customLabel\": \"Resident memory\", \"field\": \"mongodb.status.memory.resident.mb\"}}, {\"type\": \"avg\", \"enabled\": true, \"id\": \"5\", \"schema\": \"metric\", \"params\": {\"customLabel\": \"Virtual memory\", \"field\": \"mongodb.status.memory.virtual.mb\"}}]}"
            },
            "id": "MongoDB-hosts-ecs",
            "type": "visualization",
            "version": 2
        },
        {
            "attributes": {
                "description": "",
                "kibanaSavedObjectMeta": {
                    "searchSourceJSON": "{\"filter\": []}"
                },
                "savedSearchId": "MongoDB-search-ecs",
                "title": "Engine & Version [Metricbeat MongoDB] ECS",
                "uiStateJSON": "{}",
                "version": 1,
                "visState": "{\"params\": {\"shareYAxis\": true, \"addTooltip\": true, \"type\": \"pie\", \"legendPosition\": \"bottom\", \"addLegend\": true, \"isDonut\": true}, \"type\": \"pie\", \"title\": \"Engine & Version [Metricbeat MongoDB] ECS\", \"aggs\": [{\"type\": \"cardinality\", \"enabled\": true, \"id\": \"1\", \"schema\": \"metric\", \"params\": {\"field\": \"service.address\"}}, {\"type\": \"terms\", \"enabled\": true, \"id\": \"2\", \"schema\": \"segment\", \"params\": {\"orderBy\": \"1\", \"customLabel\": \"Engine\", \"size\": 5, \"order\": \"desc\", \"field\": \"mongodb.status.storage_engine.name\"}}, {\"type\": \"terms\", \"enabled\": true, \"id\": \"3\", \"schema\": \"segment\", \"params\": {\"orderBy\": \"1\", \"customLabel\": \"Version\", \"size\": 5, \"order\": \"desc\", \"field\": \"service.version\"}}]}"
            },
            "id": "MongoDB-Engine-ampersand-Version-ecs",
            "type": "visualization",
            "version": 2
        },
        {
            "attributes": {
                "description": "",
                "kibanaSavedObjectMeta": {
                    "searchSourceJSON": "{\"filter\": []}"
                },
                "savedSearchId": "MongoDB-search-ecs",
                "title": "Operation counters [Metricbeat MongoDB] ECS",
                "uiStateJSON": "{}",
                "version": 1,
                "visState": "{\"params\": {\"grid\": {\"style\": {\"color\": \"#eee\"}, \"categoryLines\": false}, \"times\": [], \"addTimeMarker\": false, \"legendPosition\": \"bottom\", \"seriesParams\": [{\"showCircles\": true, \"show\": \"true\", \"interpolate\": \"linear\", \"drawLinesBetweenPoints\": true, \"type\": \"area\", \"data\": {\"id\": \"1\", \"label\": \"Count\"}, \"mode\": \"stacked\", \"valueAxis\": \"ValueAxis-1\"}], \"setYExtents\": false, \"yAxis\": {}, \"scale\": \"linear\", \"defaultYExtents\": false, \"addTooltip\": true, \"type\": \"area\", \"shareYAxis\": true, \"smoothLines\": false, \"addLegend\": true, \"categoryAxes\": [{\"scale\": {\"type\": \"linear\"}, \"id\": \"CategoryAxis-1\", \"type\": \"category\", \"position\": \"bottom\", \"style\": {}, \"show\": true, \"labels\": {\"truncate\": 100, \"show\": true}, \"title\": {}}], \"valueAxes\": [{\"scale\": {\"type\": \"linear\", \"mode\": \"normal\"}, \"id\": \"ValueAxis-1\", \"show\": true, \"position\": \"left\", \"style\": {}, \"labels\": {\"truncate\": 100, \"show\": true, \"rotate\": 0, \"filter\": false}, \"type\": \"value\", \"name\": \"LeftAxis-1\", \"title\": {\"text\": \"Count\"}}], \"mode\": \"stacked\", \"interpolate\": \"linear\"}, \"type\": \"area\", \"title\": \"Operation counters [Metricbeat MongoDB] ECS\", \"aggs\": [{\"type\": \"avg\", \"enabled\": true, \"id\": \"1\", \"schema\": \"metric\", \"params\": {\"customLabel\": \"command\", \"field\": \"mongodb.status.ops.counters.command\"}}, {\"type\": \"date_histogram\", \"enabled\": true, \"id\": \"2\", \"schema\": \"segment\", \"params\": {\"min_doc_count\": 1, \"extended_bounds\": {}, \"interval\": \"auto\", \"customInterval\": \"2h\", \"field\": \"@timestamp\"}}, {\"type\": \"avg\", \"enabled\": true, \"id\": \"3\", \"schema\": \"metric\", \"params\": {\"customLabel\": \"delete\", \"field\": \"mongodb.status.ops.counters.delete\"}}, {\"type\": \"avg\", \"enabled\": true, \"id\": \"4\", \"schema\": \"metric\", \"params\": {\"customLabel\": \"getmore\", \"field\": \"mongodb.status.ops.counters.getmore\"}}, {\"type\": \"avg\", \"enabled\": true, \"id\": \"5\", \"schema\": \"metric\", \"params\": {\"customLabel\": \"insert\", \"field\": \"mongodb.status.ops.counters.insert\"}}, {\"type\": \"avg\", \"enabled\": true, \"id\": \"6\", \"schema\": \"metric\", \"params\": {\"customLabel\": \"query\", \"field\": \"mongodb.status.ops.counters.query\"}}, {\"type\": \"avg\", \"enabled\": true, \"id\": \"7\", \"schema\": \"metric\", \"params\": {\"customLabel\": \"update\", \"field\": \"mongodb.status.ops.replicated.update\"}}]}"
            },
            "id": "MongoDB-operation-counters-ecs",
            "type": "visualization",
            "version": 2
        },
        {
            "attributes": {
                "description": "",
                "kibanaSavedObjectMeta": {
                    "searchSourceJSON": "{\"filter\": []}"
                },
                "savedSearchId": "MongoDB-search-ecs",
                "title": "Concurrent transactions Read [Metricbeat MongoDB] ECS",
                "uiStateJSON": "{\"vis\": {\"colors\": {\"Read Used\": \"#BF1B00\", \"Read Available\": \"#508642\"}}}",
                "version": 1,
                "visState": "{\"params\": {\"grid\": {\"style\": {\"color\": \"#eee\"}, \"categoryLines\": false}, \"times\": [], \"addTimeMarker\": false, \"legendPosition\": \"bottom\", \"seriesParams\": [{\"showCircles\": true, \"show\": \"true\", \"interpolate\": \"linear\", \"drawLinesBetweenPoints\": true, \"type\": \"area\", \"data\": {\"id\": \"1\", \"label\": \"Count\"}, \"mode\": \"stacked\", \"valueAxis\": \"ValueAxis-1\"}], \"setYExtents\": false, \"yAxis\": {}, \"scale\": \"linear\", \"defaultYExtents\": false, \"addTooltip\": true, \"type\": \"area\", \"shareYAxis\": true, \"smoothLines\": false, \"addLegend\": true, \"categoryAxes\": [{\"scale\": {\"type\": \"linear\"}, \"id\": \"CategoryAxis-1\", \"type\": \"category\", \"position\": \"bottom\", \"style\": {}, \"show\": true, \"labels\": {\"truncate\": 100, \"show\": true}, \"title\": {}}], \"valueAxes\": [{\"scale\": {\"type\": \"linear\", \"mode\": \"normal\"}, \"id\": \"ValueAxis-1\", \"show\": true, \"position\": \"left\", \"style\": {}, \"labels\": {\"truncate\": 100, \"show\": true, \"rotate\": 0, \"filter\": false}, \"type\": \"value\", \"name\": \"LeftAxis-1\", \"title\": {\"text\": \"Count\"}}], \"mode\": \"stacked\", \"interpolate\": \"linear\"}, \"type\": \"area\", \"title\": \"Concurrent transactions Read [Metricbeat MongoDB] ECS\", \"aggs\": [{\"type\": \"avg\", \"enabled\": true, \"id\": \"1\", \"schema\": \"metric\", \"params\": {\"customLabel\": \"Read Available\", \"field\": \"mongodb.status.wired_tiger.concurrent_transactions.read.available\"}}, {\"type\": \"date_histogram\", \"enabled\": true, \"id\": \"2\", \"schema\": \"segment\", \"params\": {\"min_doc_count\": 1, \"extended_bounds\": {}, \"interval\": \"auto\", \"customInterval\": \"2h\", \"field\": \"@timestamp\"}}, {\"type\": \"avg\", \"enabled\": true, \"id\": \"3\", \"schema\": \"metric\", \"params\": {\"customLabel\": \"Read Used\", \"field\": \"mongodb.status.wired_tiger.concurrent_transactions.read.out\"}}]}"
            },
            "id": "MongoDB-Concurrent-transactions-Read-ecs",
            "type": "visualization",
            "version": 2
        },
        {
            "attributes": {
                "description": "",
                "kibanaSavedObjectMeta": {
                    "searchSourceJSON": "{\"filter\": []}"
                },
                "savedSearchId": "MongoDB-search-ecs",
                "title": "Concurrent transactions Write [Metricbeat MongoDB] ECS",
                "uiStateJSON": "{\"vis\": {\"colors\": {\"Write Available\": \"#629E51\", \"Write Used\": \"#BF1B00\"}}}",
                "version": 1,
                "visState": "{\"params\": {\"grid\": {\"style\": {\"color\": \"#eee\"}, \"categoryLines\": false}, \"times\": [], \"addTimeMarker\": false, \"legendPosition\": \"bottom\", \"seriesParams\": [{\"showCircles\": true, \"show\": \"true\", \"interpolate\": \"linear\", \"drawLinesBetweenPoints\": true, \"type\": \"area\", \"data\": {\"id\": \"1\", \"label\": \"Count\"}, \"mode\": \"stacked\", \"valueAxis\": \"ValueAxis-1\"}], \"setYExtents\": false, \"yAxis\": {}, \"scale\": \"linear\", \"defaultYExtents\": false, \"addTooltip\": true, \"type\": \"area\", \"shareYAxis\": true, \"smoothLines\": false, \"addLegend\": true, \"categoryAxes\": [{\"scale\": {\"type\": \"linear\"}, \"id\": \"CategoryAxis-1\", \"type\": \"category\", \"position\": \"bottom\", \"style\": {}, \"show\": true, \"labels\": {\"truncate\": 100, \"show\": true}, \"title\": {}}], \"valueAxes\": [{\"scale\": {\"type\": \"linear\", \"mode\": \"normal\"}, \"id\": \"ValueAxis-1\", \"show\": true, \"position\": \"left\", \"style\": {}, \"labels\": {\"truncate\": 100, \"show\": true, \"rotate\": 0, \"filter\": false}, \"type\": \"value\", \"name\": \"LeftAxis-1\", \"title\": {\"text\": \"Count\"}}], \"mode\": \"stacked\", \"interpolate\": \"linear\"}, \"type\": \"area\", \"title\": \"Concurrent transactions Write [Metricbeat MongoDB] ECS\", \"aggs\": [{\"type\": \"avg\", \"enabled\": true, \"id\": \"1\", \"schema\": \"metric\", \"params\": {\"customLabel\": \"Write Available\", \"field\": \"mongodb.status.wired_tiger.concurrent_transactions.write.available\"}}, {\"type\": \"date_histogram\", \"enabled\": true, \"id\": \"2\", \"schema\": \"segment\", \"params\": {\"min_doc_count\": 1, \"extended_bounds\": {}, \"interval\": \"auto\", \"customInterval\": \"2h\", \"field\": \"@timestamp\"}}, {\"type\": \"avg\", \"enabled\": true, \"id\": \"3\", \"schema\": \"metric\", \"params\": {\"customLabel\": \"Write Used\", \"field\": \"mongodb.status.wired_tiger.concurrent_transactions.write.out\"}}]}"
            },
            "id": "MongoDB-Concurrent-transactions-Write-ecs",
            "type": "visualization",
            "version": 2
        },
        {
            "attributes": {
                "description": "",
                "kibanaSavedObjectMeta": {
                    "searchSourceJSON": "{\"filter\": []}"
                },
                "savedSearchId": "MongoDB-search-ecs",
                "title": "Memory stats [Metricbeat MongoDB] ECS",
                "uiStateJSON": "{}",
                "version": 1,
                "visState": "{\"params\": {\"grid\": {\"style\": {\"color\": \"#eee\"}, \"categoryLines\": false}, \"times\": [], \"addTimeMarker\": false, \"drawLinesBetweenPoints\": true, \"legendPosition\": \"bottom\", \"seriesParams\": [{\"showCircles\": true, \"show\": \"true\", \"drawLinesBetweenPoints\": true, \"type\": \"line\", \"data\": {\"id\": \"1\", \"label\": \"Count\"}, \"mode\": \"normal\", \"valueAxis\": \"ValueAxis-1\"}], \"setYExtents\": false, \"yAxis\": {}, \"showCircles\": true, \"scale\": \"log\", \"radiusRatio\": 9, \"defaultYExtents\": false, \"addTooltip\": true, \"type\": \"line\", \"shareYAxis\": true, \"smoothLines\": false, \"addLegend\": true, \"categoryAxes\": [{\"scale\": {\"type\": \"linear\"}, \"id\": \"CategoryAxis-1\", \"type\": \"category\", \"position\": \"bottom\", \"style\": {}, \"show\": true, \"labels\": {\"truncate\": 100, \"show\": true}, \"title\": {}}], \"valueAxes\": [{\"scale\": {\"type\": \"linear\", \"mode\": \"normal\"}, \"id\": \"ValueAxis-1\", \"show\": true, \"position\": \"left\", \"style\": {}, \"labels\": {\"truncate\": 100, \"show\": true, \"rotate\": 0, \"filter\": false}, \"type\": \"value\", \"name\": \"LeftAxis-1\", \"title\": {\"text\": \"Count\"}}], \"interpolate\": \"linear\"}, \"type\": \"line\", \"title\": \"Memory stats [Metricbeat MongoDB] ECS\", \"aggs\": [{\"type\": \"avg\", \"enabled\": true, \"id\": \"1\", \"schema\": \"metric\", \"params\": {\"customLabel\": \"Mapped\", \"field\": \"mongodb.status.memory.mapped.mb\"}}, {\"type\": \"date_histogram\", \"enabled\": true, \"id\": \"2\", \"schema\": \"segment\", \"params\": {\"min_doc_count\": 1, \"extended_bounds\": {}, \"interval\": \"auto\", \"customInterval\": \"2h\", \"field\": \"@timestamp\"}}, {\"type\": \"avg\", \"enabled\": true, \"id\": \"3\", \"schema\": \"metric\", \"params\": {\"customLabel\": \"Mapped with journal\", \"field\": \"mongodb.status.memory.mapped_with_journal.mb\"}}, {\"type\": \"avg\", \"enabled\": true, \"id\": \"4\", \"schema\": \"metric\", \"params\": {\"customLabel\": \"Rezident\", \"field\": \"mongodb.status.memory.resident.mb\"}}, {\"type\": \"avg\", \"enabled\": true, \"id\": \"5\", \"schema\": \"metric\", \"params\": {\"customLabel\": \"Virtual\", \"field\": \"mongodb.status.memory.virtual.mb\"}}]}"
            },
            "id": "MongoDB-memory-stats-ecs",
            "type": "visualization",
            "version": 2
        },
        {
            "attributes": {
                "description": "",
                "kibanaSavedObjectMeta": {
                    "searchSourceJSON": "{\"filter\": []}"
                },
                "savedSearchId": "MongoDB-search-ecs",
                "title": "Asserts [Metricbeat MongoDB] ECS",
                "uiStateJSON": "{}",
                "version": 1,
                "visState": "{\"params\": {\"grid\": {\"style\": {\"color\": \"#eee\"}, \"categoryLines\": false}, \"times\": [], \"addTimeMarker\": false, \"legendPosition\": \"bottom\", \"seriesParams\": [{\"showCircles\": true, \"show\": \"true\", \"interpolate\": \"linear\", \"drawLinesBetweenPoints\": true, \"type\": \"area\", \"data\": {\"id\": \"1\", \"label\": \"Count\"}, \"mode\": \"stacked\", \"valueAxis\": \"ValueAxis-1\"}], \"setYExtents\": false, \"yAxis\": {}, \"scale\": \"linear\", \"defaultYExtents\": false, \"addTooltip\": true, \"type\": \"area\", \"shareYAxis\": true, \"smoothLines\": false, \"addLegend\": true, \"categoryAxes\": [{\"scale\": {\"type\": \"linear\"}, \"id\": \"CategoryAxis-1\", \"type\": \"category\", \"position\": \"bottom\", \"style\": {}, \"show\": true, \"labels\": {\"truncate\": 100, \"show\": true}, \"title\": {}}], \"valueAxes\": [{\"scale\": {\"type\": \"linear\", \"mode\": \"normal\"}, \"id\": \"ValueAxis-1\", \"show\": true, \"position\": \"left\", \"style\": {}, \"labels\": {\"truncate\": 100, \"show\": true, \"rotate\": 0, \"filter\": false}, \"type\": \"value\", \"name\": \"LeftAxis-1\", \"title\": {\"text\": \"Count\"}}], \"mode\": \"stacked\", \"interpolate\": \"linear\"}, \"type\": \"area\", \"title\": \"Asserts [Metricbeat MongoDB] ECS\", \"aggs\": [{\"type\": \"max\", \"enabled\": true, \"id\": \"1\", \"schema\": \"metric\", \"params\": {\"customLabel\": \"message\", \"field\": \"mongodb.status.asserts.msg\"}}, {\"type\": \"date_histogram\", \"enabled\": true, \"id\": \"2\", \"schema\": \"segment\", \"params\": {\"min_doc_count\": 1, \"extended_bounds\": {}, \"interval\": \"auto\", \"customInterval\": \"2h\", \"field\": \"@timestamp\"}}, {\"type\": \"max\", \"enabled\": true, \"id\": \"3\", \"schema\": \"metric\", \"params\": {\"customLabel\": \"regular\", \"field\": \"mongodb.status.asserts.regular\"}}, {\"type\": \"max\", \"enabled\": true, \"id\": \"4\", \"schema\": \"metric\", \"params\": {\"customLabel\": \"rollover\", \"field\": \"mongodb.status.asserts.rollovers\"}}, {\"type\": \"max\", \"enabled\": true, \"id\": \"5\", \"schema\": \"metric\", \"params\": {\"customLabel\": \"user\", \"field\": \"mongodb.status.asserts.user\"}}, {\"type\": \"max\", \"enabled\": true, \"id\": \"6\", \"schema\": \"metric\", \"params\": {\"customLabel\": \"warning\", \"field\": \"mongodb.status.asserts.warning\"}}]}"
            },
            "id": "MongoDB-asserts-ecs",
            "type": "visualization",
            "version": 2
        },
        {
            "attributes": {
                "description": "",
                "kibanaSavedObjectMeta": {
                    "searchSourceJSON": "{\"filter\": []}"
                },
                "savedSearchId": "MongoDB-search-ecs",
                "title": "WiredTiger Cache [Metricbeat MongoDB] ECS",
                "uiStateJSON": "{}",
                "version": 1,
                "visState": "{\"params\": {\"grid\": {\"style\": {\"color\": \"#eee\"}, \"categoryLines\": false}, \"times\": [], \"addTimeMarker\": false, \"legendPosition\": \"bottom\", \"seriesParams\": [{\"showCircles\": true, \"show\": \"true\", \"interpolate\": \"linear\", \"drawLinesBetweenPoints\": true, \"type\": \"area\", \"data\": {\"id\": \"1\", \"label\": \"Count\"}, \"mode\": \"stacked\", \"valueAxis\": \"ValueAxis-1\"}], \"setYExtents\": false, \"yAxis\": {}, \"scale\": \"linear\", \"defaultYExtents\": false, \"addTooltip\": true, \"type\": \"area\", \"shareYAxis\": true, \"smoothLines\": false, \"addLegend\": true, \"categoryAxes\": [{\"scale\": {\"type\": \"linear\"}, \"id\": \"CategoryAxis-1\", \"type\": \"category\", \"position\": \"bottom\", \"style\": {}, \"show\": true, \"labels\": {\"truncate\": 100, \"show\": true}, \"title\": {}}], \"valueAxes\": [{\"scale\": {\"type\": \"linear\", \"mode\": \"normal\"}, \"id\": \"ValueAxis-1\", \"show\": true, \"position\": \"left\", \"style\": {}, \"labels\": {\"truncate\": 100, \"show\": true, \"rotate\": 0, \"filter\": false}, \"type\": \"value\", \"name\": \"LeftAxis-1\", \"title\": {\"text\": \"Count\"}}], \"mode\": \"overlap\", \"interpolate\": \"linear\"}, \"type\": \"area\", \"title\": \"WiredTiger Cache [Metricbeat MongoDB] ECS\", \"aggs\": [{\"type\": \"avg\", \"enabled\": true, \"id\": \"1\", \"schema\": \"metric\", \"params\": {\"customLabel\": \"max\", \"field\": \"mongodb.status.wired_tiger.cache.maximum.bytes\"}}, {\"type\": \"date_histogram\", \"enabled\": true, \"id\": \"2\", \"schema\": \"segment\", \"params\": {\"min_doc_count\": 1, \"extended_bounds\": {}, \"interval\": \"auto\", \"customInterval\": \"2h\", \"field\": \"@timestamp\"}}, {\"type\": \"avg\", \"enabled\": true, \"id\": \"3\", \"schema\": \"metric\", \"params\": {\"customLabel\": \"used\", \"field\": \"mongodb.status.wired_tiger.cache.used.bytes\"}}, {\"type\": \"avg\", \"enabled\": true, \"id\": \"4\", \"schema\": \"metric\", \"params\": {\"customLabel\": \"dirty\", \"field\": \"mongodb.status.wired_tiger.cache.dirty.bytes\"}}]}"
            },
            "id": "MongoDB-WiredTiger-Cache-ecs",
            "type": "visualization",
            "version": 2
        },
        {
            "attributes": {
                "columns": [
                    "_source"
                ],
                "description": "",
                "hits": 0,
                "kibanaSavedObjectMeta": {
                    "searchSourceJSON": "{\"query\": {\"query\": \"event.module:mongodb\", \"language\": \"kuery\"}, \"highlight\": {\"post_tags\": [\"@/kibana-highlighted-field@\"], \"pre_tags\": [\"@kibana-highlighted-field@\"], \"fragment_size\": 2147483647, \"require_field_match\": false, \"fields\": {\"*\": {}}}, \"index\": \"metricbeat-*\", \"filter\": []}"
                },
                "sort": [
                    "@timestamp",
                    "desc"
                ],
                "title": "MongoDB search ECS",
                "version": 1
            },
            "id": "MongoDB-search-ecs",
            "type": "search",
            "version": 1
        },
        {
            "attributes": {
                "description": "Overview of MongoDB server status",
                "hits": 0,
                "kibanaSavedObjectMeta": {
                    "searchSourceJSON": "{\"query\": {\"query\": \"\", \"language\": \"kuery\"}, \"version\": true, \"highlightAll\": true, \"filter\": []}"
                },
                "optionsJSON": "{\"darkTheme\": false}",
                "panelsJSON": "[{\"size_x\": 8, \"id\": \"MongoDB-hosts-ecs\", \"type\": \"visualization\", \"col\": 1, \"panelIndex\": 1, \"row\": 1, \"size_y\": 3}, {\"size_x\": 4, \"id\": \"MongoDB-Engine-ampersand-Version-ecs\", \"type\": \"visualization\", \"col\": 9, \"panelIndex\": 4, \"row\": 1, \"size_y\": 3}, {\"size_x\": 6, \"id\": \"MongoDB-operation-counters-ecs\", \"type\": \"visualization\", \"col\": 1, \"panelIndex\": 2, \"row\": 4, \"size_y\": 3}, {\"size_x\": 3, \"id\": \"MongoDB-Concurrent-transactions-Read-ecs\", \"type\": \"visualization\", \"col\": 7, \"panelIndex\": 6, \"row\": 4, \"size_y\": 3}, {\"size_x\": 3, \"id\": \"MongoDB-Concurrent-transactions-Write-ecs\", \"type\": \"visualization\", \"col\": 10, \"panelIndex\": 7, \"row\": 4, \"size_y\": 3}, {\"size_x\": 12, \"id\": \"MongoDB-memory-stats-ecs\", \"type\": \"visualization\", \"col\": 1, \"panelIndex\": 5, \"row\": 10, \"size_y\": 4}, {\"size_x\": 6, \"id\": \"MongoDB-asserts-ecs\", \"type\": \"visualization\", \"col\": 7, \"panelIndex\": 3, \"row\": 7, \"size_y\": 3}, {\"size_x\": 6, \"id\": \"MongoDB-WiredTiger-Cache-ecs\", \"type\": \"visualization\", \"col\": 1, \"panelIndex\": 8, \"row\": 7, \"size_y\": 3}]",
                "timeRestore": false,
                "title": "[Metricbeat MongoDB] Overview ECS",
                "uiStateJSON": "{\"P-1\": {\"vis\": {\"params\": {\"sort\": {\"columnIndex\": null, \"direction\": null}}}}}",
                "version": 1
            },
            "id": "Metricbeat-MongoDB-ecs",
            "type": "dashboard",
            "version": 3
        }
    ],
    "version": "6.0.0-beta1-SNAPSHOT"
}